MANIFEST.in
README.rst
manage.py
requirements.txt
setup.cfg
setup.py
EBMPICO/__init__.py
EBMPICO/settings.py
EBMPICO/urls.py
EBMPICO/wsgi.py
LSTMCRFApp/__init__.py
LSTMCRFApp/admin.py
LSTMCRFApp/apps.py
LSTMCRFApp/build_data_hirech.py
LSTMCRFApp/build_training_set.py
LSTMCRFApp/ebm_nlp_demo.py
LSTMCRFApp/generate_bio_labels.py
LSTMCRFApp/middleware.py
LSTMCRFApp/models.py
LSTMCRFApp/serializers.py
LSTMCRFApp/test_in.py
LSTMCRFApp/tests.py
LSTMCRFApp/urls.py
LSTMCRFApp/views.py
build_data/__init__.py
build_data/build_corpus.py
build_data/build_data.py
build_data/pico_detailed_tagger.json
build_data/result1.json
lstm_crf/LICENSE.txt
lstm_crf/README.md
lstm_crf/__init__.py
lstm_crf/build_data.py
lstm_crf/eval.sh
lstm_crf/eval_c.py
lstm_crf/evaluate.py
lstm_crf/makefile
lstm_crf/predict.py
lstm_crf/train.py
lstm_crf/model/__init__.py
lstm_crf/model/base_model.py
lstm_crf/model/config.py
lstm_crf/model/data_utils.py
lstm_crf/model/eval_c.py
lstm_crf/model/general_utils.py
lstm_crf/model/ner_model.py
pico/__init__.py
pico/__main__.py
pico/pico_detect.py
picodetection.egg-info/PKG-INFO
picodetection.egg-info/SOURCES.txt
picodetection.egg-info/dependency_links.txt
picodetection.egg-info/entry_points.txt
picodetection.egg-info/requires.txt
picodetection.egg-info/top_level.txt
tags/__init__.py
tags/tag.py